smartworks/__init__.py
smartworks/ecp/__init__.py
smartworks/ecp/action.py
smartworks/ecp/amqp.py
smartworks/ecp/api.py
smartworks/ecp/base_pubsub.py
smartworks/ecp/credentials.py
smartworks/ecp/deployment.py
smartworks/ecp/driver.py
smartworks/ecp/event.py
smartworks/ecp/health.py
smartworks/ecp/label.py
smartworks/ecp/telemetry.py
smartworks/ecp/thing.py
altair_smartworks_ecp_client-0.5.3.dist-info/LICENSE
altair_smartworks_ecp_client-0.5.3.dist-info/WHEEL
altair_smartworks_ecp_client-0.5.3.dist-info/METADATA
altair_smartworks_ecp_client-0.5.3.dist-info/RECORD
